README.rst
setup.py
txscrypt/__init__.py
txscrypt/_version.py
txscrypt/wrapper.py
txscrypt.egg-info/PKG-INFO
txscrypt.egg-info/SOURCES.txt
txscrypt.egg-info/dependency_links.txt
txscrypt.egg-info/requires.txt
txscrypt.egg-info/top_level.txt
txscrypt/test/__init__.py
txscrypt/test/test_wrapper.py