Metadata-Version: 1.1
Name: txscrypt
Version: 1.1.1
Summary: Twisted wrapper for scrypt
Home-page: https://github.com/lvh/txscrypt
Author: Laurens Van Houtven
Author-email: _@lvh.cc
License: ISC
Platform: UNKNOWN
Classifier: Development Status :: 3 - Alpha
Classifier: Framework :: Twisted
Classifier: License :: OSI Approved :: ISC License (ISCL)
